bluetooth_clocks/__init__.py
bluetooth_clocks/__main__.py
bluetooth_clocks/exceptions.py
bluetooth_clocks/py.typed
bluetooth_clocks/scanners.py
bluetooth_clocks/devices/__init__.py
bluetooth_clocks/devices/current_time_service.py
bluetooth_clocks/devices/pvvx.py
bluetooth_clocks/devices/qingping.py
bluetooth_clocks/devices/thermopro.py
bluetooth_clocks/devices/xiaomi.py
bluetooth_clocks-0.2.0.dist-info/LICENSE.txt
bluetooth_clocks-0.2.0.dist-info/METADATA
bluetooth_clocks-0.2.0.dist-info/WHEEL
bluetooth_clocks-0.2.0.dist-info/entry_points.txt
bluetooth_clocks-0.2.0.dist-info/top_level.txt
bluetooth_clocks-0.2.0.dist-info/RECORD
