Metadata-Version: 2.1
Name: bluetooth-clocks
Version: 0.2.0
Summary: Set and get the time on various Bluetooth Low Energy clocks
Home-page: https://github.com/koenvervloesem/bluetooth-clocks
Author: Koen Vervloesem
Author-email: koen@vervloesem.eu
License: MIT
Project-URL: Documentation, https://bluetooth-clocks.readthedocs.io/
Project-URL: Source, https://github.com/koenvervloesem/bluetooth-clocks
Project-URL: Changelog, https://github.com/koenvervloesem/bluetooth-clocks/blob/main/CHANGELOG.rst
Project-URL: Tracker, https://github.com/koenvervloesem/bluetooth-clocks/issues
Project-URL: Download, https://pypi.org/project/bluetooth-clocks/#files
Keywords: bluetooth,ble,bluetooth-low-energy,clocks,time,time-synchronization,get-time,set-time,current-time-service
Platform: any
Classifier: Development Status :: 4 - Beta
Classifier: Environment :: Console
Classifier: Intended Audience :: Developers
Classifier: License :: OSI Approved :: MIT License
Classifier: Operating System :: MacOS
Classifier: Operating System :: Microsoft :: Windows
Classifier: Operating System :: POSIX :: Linux
Classifier: Programming Language :: Python
Classifier: Programming Language :: Python :: 3
Classifier: Programming Language :: Python :: 3 :: Only
Classifier: Programming Language :: Python :: 3.8
Classifier: Programming Language :: Python :: 3.9
Classifier: Programming Language :: Python :: 3.10
Classifier: Programming Language :: Python :: 3.11
Classifier: Topic :: Software Development :: Libraries
Classifier: Topic :: Software Development :: Libraries :: Python Modules
Classifier: Topic :: Utilities
Requires-Python: >=3.8
License-File: LICENSE.txt
Requires-Dist: bleak (>=0.19.0)
Provides-Extra: testing
Requires-Dist: setuptools ; extra == 'testing'
Requires-Dist: pytest ; extra == 'testing'
Requires-Dist: pytest-cov ; extra == 'testing'
Requires-Dist: time-machine ; extra == 'testing'
Requires-Dist: tzdata ; extra == 'testing'
Requires-Dist: backports-zoneinfo ; (python_version < "3.9") and extra == 'testing'
